prob_conf_mat/__init__.py
prob_conf_mat/config.py
prob_conf_mat/experiment.py
prob_conf_mat/experiment_group.py
prob_conf_mat/io.py
prob_conf_mat/py.typed
prob_conf_mat/study.py
prob_conf_mat/experiment_aggregation/__init__.py
prob_conf_mat/experiment_aggregation/abc.py
prob_conf_mat/experiment_aggregation/aggregators.py
prob_conf_mat/experiment_aggregation/heterogeneity.py
prob_conf_mat/experiment_aggregation/interface.py
prob_conf_mat/experiment_comparison/__init__.py
prob_conf_mat/experiment_comparison/listwise.py
prob_conf_mat/experiment_comparison/pairwise.py
prob_conf_mat/metrics/__init__.py
prob_conf_mat/metrics/_metrics.py
prob_conf_mat/metrics/abc.py
prob_conf_mat/metrics/averaging.py
prob_conf_mat/metrics/collection.py
prob_conf_mat/metrics/interface.py
prob_conf_mat/metrics/experimental_metrics/__init__.py
prob_conf_mat/metrics/experimental_metrics/f1_gain.py
prob_conf_mat/stats/__init__.py
prob_conf_mat/stats/batched_averaging.py
prob_conf_mat/stats/dirichlet_distribution.py
prob_conf_mat/stats/hdi_estimation.py
prob_conf_mat/stats/kde.py
prob_conf_mat/stats/mode_estimation.py
prob_conf_mat/stats/probability.py
prob_conf_mat/stats/score_interval.py
prob_conf_mat/stats/summary.py
prob_conf_mat/stats/truncated_sampling.py
prob_conf_mat/utils/__init__.py
prob_conf_mat/utils/cache.py
prob_conf_mat/utils/formatting.py
prob_conf_mat/utils/rng.py
prob_conf_mat/utils/typing.py
prob_conf_mat-0.3.0.dist-info/METADATA
prob_conf_mat-0.3.0.dist-info/WHEEL
prob_conf_mat-0.3.0.dist-info/licenses/LICENSE
prob_conf_mat-0.3.0.dist-info/RECORD
