Metadata-Version: 2.4
Name: prob-conf-mat
Version: 0.3.0
Summary: Confusion matrices with uncertainty quantification, experiment aggregation and significance testing.
Project-URL: Homepage, https://pcm.ivoverhoeven.nl/
Project-URL: Documentation, https://pcm.ivoverhoeven.nl/
Project-URL: Repository, https://github.com/ioverho/prob_conf_mat
Project-URL: Issues, https://github.com/ioverho/prob_conf_mat/issues
Author-email: Ivo Verhoeven <mail@ivoverhoeven.nl>
License: MIT License
License-File: LICENSE
Keywords: classification,confusion matrices,confusion matrix,probabilistic,statistics
Classifier: Development Status :: 4 - Beta
Classifier: License :: OSI Approved :: MIT License
Classifier: Natural Language :: English
Classifier: Operating System :: OS Independent
Classifier: Programming Language :: Python :: 3
Classifier: Topic :: Scientific/Engineering :: Artificial Intelligence
Classifier: Topic :: Scientific/Engineering :: Information Analysis
Classifier: Topic :: Scientific/Engineering :: Visualization
Classifier: Typing :: Typed
Requires-Python: >=3.11
Requires-Dist: jaxtyping>=0.2.32
Requires-Dist: matplotlib>=3.7
Requires-Dist: numpy
Requires-Dist: scipy>=1.10
Requires-Dist: tabulate>=0.9
